{
  "editor": {
    "allAngles": false,
    "entityTextureMode": false
  },
  "textureWidth": 16,
  "textureHeight": 16,
  "textureSizes": {

  },
  "textures": {
    "cork": "fishing:cork",
    "glass": "fishing:glass",
    "solution": "fishing:solution"
  },
  "elements": [
    {
      "name": "Contents",
      "renderPass": 3,
      "from": [6.5, 0.7, 6.5],
      "to": [9.5, 10.7, 9.5],
      "rotationOrigin": [6.5, 0.7, 6.5],
      "faces": {
        "north": { "texture": "#solution", "uv": [0.0, 0.0, 3.0, 10.0] },
        "east": { "texture": "#solution", "uv": [0.0, 0.0, 3.0, 10.0] },
        "south": { "texture": "#solution", "uv": [0.0, 0.0, 3.0, 10.0] },
        "west": { "texture": "#solution", "uv": [0.0, 0.0, 3.0, 10.0] },
        "up": { "texture": "#solution", "uv": [0.0, 0.0, 3.0, 3.0] },
        "down": { "texture": "#solution", "uv": [0.0, 0.0, 3.0, 3.0] }
      }
    },
    {
      "name": "Base",
      "renderPass": 3,
      "from": [6.0, 0.0, 6.0],
      "to": [10.0, 0.6, 10.0],
      "rotationOrigin": [6.0, 0.0, 6.0],
      "faces": {
        "north": { "texture": "#glass", "uv": [0.0, 0.0, 4.0, 0.5] },
        "east": { "texture": "#glass", "uv": [0.0, 0.0, 4.0, 0.5] },
        "south": { "texture": "#glass", "uv": [0.0, 0.0, 4.0, 0.5] },
        "west": { "texture": "#glass", "uv": [0.0, 0.0, 4.0, 0.5] },
        "up": { "texture": "#glass", "uv": [0.0, 0.0, 4.0, 4.0] },
        "down": { "texture": "#glass", "uv": [0.0, 0.0, 4.0, 4.0] }
      },
      "children": [
        {
          "name": "Face1",
          "renderPass": 3,
          "from": [0.0, 0.6, 0.0],
          "to": [4.0, 12.6, 0.4],
          "rotationOrigin": [0.0, 0.6, 0.0],
          "faces": {
            "north": { "texture": "#glass", "uv": [0.0, 0.0, 4.0, 12.0] },
            "east": { "texture": "#glass", "uv": [0.0, 0.0, 0.5, 12.0] },
            "south": { "texture": "#glass", "uv": [0.0, 0.0, 4.0, 12.0] },
            "west": { "texture": "#glass", "uv": [0.0, 0.0, 0.5, 12.0] },
            "up": { "texture": "#glass", "uv": [0.0, 0.0, 4.0, 0.5] }
          }
        },
        {
          "name": "Face2",
          "renderPass": 3,
          "from": [0.0, 0.6, 3.6],
          "to": [4.0, 12.6, 4.0],
          "rotationOrigin": [0.0, 0.6, 3.6],
          "faces": {
            "north": { "texture": "#glass", "uv": [0.0, 0.0, 4.0, 12.0] },
            "east": { "texture": "#glass", "uv": [0.0, 0.0, 0.5, 12.0] },
            "south": { "texture": "#glass", "uv": [0.0, 0.0, 4.0, 12.0] },
            "west": { "texture": "#glass", "uv": [0.0, 0.0, 0.5, 12.0] },
            "up": { "texture": "#glass", "uv": [0.0, 0.0, 4.0, 0.5] }
          }
        },
        {
          "name": "Face3",
          "renderPass": 3,
          "from": [0.0, 0.6, 0.4],
          "to": [0.4, 12.6, 3.6],
          "rotationOrigin": [0.0, 0.6, 0.4],
          "faces": {
            "east": { "texture": "#glass", "uv": [0.0, 0.0, 3.0, 12.0] },
            "west": { "texture": "#glass", "uv": [0.0, 0.0, 3.0, 12.0], "windMode": [-1, -1, -1, -1] },
            "up": { "texture": "#glass", "uv": [0.0, 0.0, 0.5, 3.0] }
          }
        },
        {
          "name": "Face4",
          "renderPass": 3,
          "from": [3.6, 0.6, 0.4],
          "to": [4.0, 12.6, 3.6],
          "rotationOrigin": [3.6, 0.6, 0.4],
          "faces": {
            "east": { "texture": "#glass", "uv": [0.0, 0.0, 3.0, 12.0] },
            "west": { "texture": "#glass", "uv": [0.0, 0.0, 3.0, 12.0] },
            "up": { "texture": "#glass", "uv": [0.0, 0.0, 0.5, 3.0] }
          }
        },
        {
          "name": "Cork",
          "from": [0.3, 11.6, 0.3],
          "to": [3.7, 13.6, 3.7],
          "rotationOrigin": [0.3, 11.6, 0.3],
          "faces": {
            "north": { "texture": "#cork", "uv": [0.0, 0.0, 3.0, 2.0] },
            "east": { "texture": "#cork", "uv": [0.0, 0.0, 3.0, 2.0] },
            "south": { "texture": "#cork", "uv": [0.0, 0.0, 3.0, 2.0] },
            "west": { "texture": "#cork", "uv": [0.0, 0.0, 3.0, 2.0] },
            "up": { "texture": "#cork", "uv": [0.0, 0.0, 3.0, 3.0] },
            "down": { "texture": "#cork", "uv": [0.0, 0.0, 3.0, 3.0] }
          }
        }
      ]
    }
  ]
}