{
  "editor": {
    "allAngles": false,
    "entityTextureMode": false
  },
  "textureWidth": 16,
  "textureHeight": 16,
  "textureSizes": {
    "glass": [16, 16],
    "heatpipe": [16, 16],
    "metalcopper": [32, 32]
  },
  "textures": {
    "glass": "fishing:glass",
    "heatpipe": "fishing:heatpipe"
  },
  "elements": [
    {
      "name": "Base",
      "from": [5.0, 3.0, 5.0],
      "to": [11.0, 15.0, 11.0],
      "renderPass": 3,
      "rotationOrigin": [5.0, 3.0, 5.0],
      "faces": {
        "north": { "texture": "#glass", "uv": [0.0, 0.0, 6.0, 12.0] },
        "east": { "texture": "#glass", "uv": [0.0, 0.0, 6.0, 12.0] },
        "south": { "texture": "#glass", "uv": [0.0, 0.0, 6.0, 12.0] },
        "west": { "texture": "#glass", "uv": [0.0, 0.0, 6.0, 12.0] },
        "up": { "texture": "#glass", "uv": [0.0, 0.0, 6.0, 6.0] },
        "down": { "texture": "#glass", "uv": [0.0, 0.0, 6.0, 6.0] }
      },
      "children": [
        {
          "name": "HeatPad",
          "from": [0.2, -0.5, 0.2],
          "to": [5.8, 0.5, 5.8],
          "rotationOrigin": [-1.8, -0.5, -1.8],
          "faces": {
            "north": { "texture": "#heatpipe", "uv": [0.0, 0.0, 5.5, 1.0] },
            "east": { "texture": "#heatpipe", "uv": [0.0, 0.0, 5.5, 1.0] },
            "south": { "texture": "#heatpipe", "uv": [0.0, 0.0, 5.5, 1.0] },
            "west": { "texture": "#heatpipe", "uv": [0.0, 0.0, 5.5, 1.0] },
            "up": { "texture": "#heatpipe", "uv": [0.0, 0.0, 5.5, 5.5] },
            "down": { "texture": "#heatpipe", "uv": [0.0, 0.0, 5.5, 5.5] }
          }
        },
        {
          "name": "Cork2",
          "from": [1.8, 11.2, 1.8],
          "to": [4.2, 13.2, 4.2],
          "rotationOrigin": [1.8, 11.2, 1.8],
          "faces": {
            "north": { "texture": "#heatpipe", "uv": [0.0, 0.0, 2.0, 2.0] },
            "east": { "texture": "#heatpipe", "uv": [0.0, 0.0, 2.0, 2.0] },
            "south": { "texture": "#heatpipe", "uv": [0.0, 0.0, 2.0, 2.0] },
            "west": { "texture": "#heatpipe", "uv": [0.0, 0.0, 2.0, 2.0] },
            "up": { "texture": "#heatpipe", "uv": [0.0, 0.0, 2.0, 2.0] },
            "down": { "texture": "#heatpipe", "uv": [0.0, 0.0, 2.0, 2.0] }
          }
        }
      ]
    },
    {
      "name": "Leg1",
      "from": [3.5, 0.0, 3.5],
      "to": [5.5, 4.0, 5.5],
      "rotationOrigin": [3.5, 0.0, 3.5],
      "faces": {
        "north": { "texture": "#heatpipe", "uv": [0.0, 0.0, 2.0, 4.0] },
        "east": { "texture": "#heatpipe", "uv": [0.0, 0.0, 2.0, 4.0] },
        "south": { "texture": "#heatpipe", "uv": [0.0, 0.0, 2.0, 4.0] },
        "west": { "texture": "#heatpipe", "uv": [0.0, 0.0, 2.0, 4.0] },
        "up": { "texture": "#heatpipe", "uv": [0.0, 0.0, 2.0, 2.0] },
        "down": { "texture": "#heatpipe", "uv": [0.0, 0.0, 2.0, 2.0] }
      }
    },
    {
      "name": "Leg2",
      "from": [10.5, 0.0, 3.5],
      "to": [12.5, 4.0, 5.5],
      "rotationOrigin": [10.5, 0.0, 3.5],
      "faces": {
        "north": { "texture": "#heatpipe", "uv": [0.0, 0.0, 2.0, 4.0] },
        "east": { "texture": "#heatpipe", "uv": [0.0, 0.0, 2.0, 4.0] },
        "south": { "texture": "#heatpipe", "uv": [0.0, 0.0, 2.0, 4.0] },
        "west": { "texture": "#heatpipe", "uv": [0.0, 0.0, 2.0, 4.0] },
        "up": { "texture": "#heatpipe", "uv": [0.0, 0.0, 2.0, 2.0] },
        "down": { "texture": "#heatpipe", "uv": [0.0, 0.0, 2.0, 2.0] }
      }
    },
    {
      "name": "Leg3",
      "from": [10.5, 0.0, 10.5],
      "to": [12.5, 4.0, 12.5],
      "rotationOrigin": [10.5, 0.0, 10.5],
      "faces": {
        "north": { "texture": "#heatpipe", "uv": [0.0, 0.0, 2.0, 4.0] },
        "east": { "texture": "#heatpipe", "uv": [0.0, 0.0, 2.0, 4.0] },
        "south": { "texture": "#heatpipe", "uv": [0.0, 0.0, 2.0, 4.0] },
        "west": { "texture": "#heatpipe", "uv": [0.0, 0.0, 2.0, 4.0] },
        "up": { "texture": "#heatpipe", "uv": [0.0, 0.0, 2.0, 2.0] },
        "down": { "texture": "#heatpipe", "uv": [0.0, 0.0, 2.0, 2.0] }
      }
    },
    {
      "name": "Leg4",
      "from": [3.5, 0.0, 10.5],
      "to": [5.5, 4.0, 12.5],
      "rotationOrigin": [3.5, 0.0, 10.5],
      "faces": {
        "north": { "texture": "#heatpipe", "uv": [0.0, 0.0, 2.0, 4.0] },
        "east": { "texture": "#heatpipe", "uv": [0.0, 0.0, 2.0, 4.0] },
        "south": { "texture": "#heatpipe", "uv": [0.0, 0.0, 2.0, 4.0] },
        "west": { "texture": "#heatpipe", "uv": [0.0, 0.0, 2.0, 4.0] },
        "up": { "texture": "#heatpipe", "uv": [0.0, 0.0, 2.0, 2.0] },
        "down": { "texture": "#heatpipe", "uv": [0.0, 0.0, 2.0, 2.0] }
      }
    },
    {
      "name": "Base3",
      "from": [7.0, 6.0, 10.0],
      "to": [9.0, 9.0, 12.0],
      "renderPass": 3,
      "rotationOrigin": [7.0, 6.0, 10.0],
      "rotationX": 90.0,
      "faces": {
        "north": { "texture": "#glass", "uv": [0.0, 0.0, 2.0, 3.0] },
        "east": { "texture": "#glass", "uv": [0.0, 0.0, 2.0, 3.0] },
        "south": { "texture": "#glass", "uv": [0.0, 0.0, 2.0, 3.0] },
        "west": { "texture": "#glass", "uv": [0.0, 0.0, 2.0, 3.0] },
        "up": { "texture": "#glass", "uv": [0.0, 0.0, 2.0, 2.0] },
        "down": { "texture": "#glass", "uv": [0.0, 0.0, 2.0, 2.0] }
      },
      "children": [
        {
          "name": "Cork",
          "from": [-0.2, 2.4, -0.2],
          "to": [2.2, 4.4, 2.2],
          "rotationOrigin": [-0.2, 2.4, -0.2],
          "faces": {
            "north": { "texture": "#heatpipe", "uv": [0.0, 0.0, 2.0, 2.0] },
            "east": { "texture": "#heatpipe", "uv": [0.0, 0.0, 2.0, 2.0] },
            "south": { "texture": "#heatpipe", "uv": [0.0, 0.0, 2.0, 2.0] },
            "west": { "texture": "#heatpipe", "uv": [0.0, 0.0, 2.0, 2.0] },
            "up": { "texture": "#heatpipe", "uv": [0.0, 0.0, 2.0, 2.0] },
            "down": { "texture": "#heatpipe", "uv": [0.0, 0.0, 2.0, 2.0] }
          }
        }
      ]
    }
  ]
}